README.md
setup.cfg
setup.py
Flask_Fulfil.egg-info/PKG-INFO
Flask_Fulfil.egg-info/SOURCES.txt
Flask_Fulfil.egg-info/dependency_links.txt
Flask_Fulfil.egg-info/not-zip-safe
Flask_Fulfil.egg-info/requires.txt
Flask_Fulfil.egg-info/top_level.txt
flask_fulfil/__init__.py
flask_fulfil/utils.py