Metadata-Version: 1.1
Name: Flask-Fulfil
Version: 0.3.2
Summary: Fulfil.IO for Flask Apps
Home-page: https://github.com/fulfilio/flask-fulfil
Author: Fulfil.IO Inc.
Author-email: hello@fulfil.io
License: BSD
Platform: any
Classifier: Environment :: Web Environment
Classifier: Intended Audience :: Developers
Classifier: License :: OSI Approved :: BSD License
Classifier: Operating System :: OS Independent
Classifier: Programming Language :: Python
Classifier: Topic :: Internet :: WWW/HTTP :: Dynamic Content
Classifier: Topic :: Software Development :: Libraries :: Python Modules
